nebula_dgl/__init__.py
nebula_dgl/nebula_exporter.py
nebula_dgl/nebula_loader.py
nebula_dgl/nebula_part_loader.py
nebula_dgl/nebula_reduced_loader.py
nebula_dgl-0.1.2.dist-info/WHEEL
nebula_dgl-0.1.2.dist-info/METADATA
nebula_dgl-0.1.2.dist-info/licenses/LICENSE
nebula_dgl-0.1.2.dist-info/RECORD
