Metadata-Version: 2.1
Name: nebula-dgl
Version: 0.1.2
Summary: Lib for NebulaGraph integration with Deep Graph Library (DGL).
License: Apache-2.0
Author-email: Wey Gu <weyl.gu@gmail.com>
Requires-Dist: nebula3-python
